MANIFEST.in
README.rst
setup.py
naudio/__init__.py
naudio/plugin.py
naudio/assets/the-price-is-right-busy.ogg
naudio/assets/the-price-is-right-failure.ogg
naudio/assets/the-price-is-right-success.ogg
nose_audio.egg-info/PKG-INFO
nose_audio.egg-info/SOURCES.txt
nose_audio.egg-info/dependency_links.txt
nose_audio.egg-info/entry_points.txt
nose_audio.egg-info/not-zip-safe
nose_audio.egg-info/pbr.json
nose_audio.egg-info/requires.txt
nose_audio.egg-info/top_level.txt