Metadata-Version: 1.1
Name: nose-audio
Version: 0.4
Summary: Add audio to your test suite
Home-page: http://github.com/ralphbean/nose-audio/
Author: Ralph Bean
Author-email: rbean@redhat.com
License: LGPLv2+
Platform: UNKNOWN
Classifier: Programming Language :: Python :: 2
Classifier: Programming Language :: Python :: 3
Classifier: Topic :: Software Development :: Testing
